CHANGELOG.rst
MANIFEST.in
README.rst
setup.py
src/sact/__init__.py
src/sact.recipe.jinjatemplate.egg-info/PKG-INFO
src/sact.recipe.jinjatemplate.egg-info/SOURCES.txt
src/sact.recipe.jinjatemplate.egg-info/dependency_links.txt
src/sact.recipe.jinjatemplate.egg-info/entry_points.txt
src/sact.recipe.jinjatemplate.egg-info/namespace_packages.txt
src/sact.recipe.jinjatemplate.egg-info/not-zip-safe
src/sact.recipe.jinjatemplate.egg-info/requires.txt
src/sact.recipe.jinjatemplate.egg-info/top_level.txt
src/sact/recipe/__init__.py
src/sact/recipe/jinjatemplate/__init__.py
src/sact/recipe/jinjatemplate/tests.py