Metadata-Version: 1.1
Name: sact.recipe.jinjatemplate
Version: 1.2
Summary: Buildout recipe for making files out of Jinja2 templates
Home-page: http://github.com/securactive/sact.recipe.jinjatemplate
Author: Securactive
Author-email: dev@securative.net
License: BSD
Keywords: zc.buildout recipe template Jinja2
Platform: UNKNOWN
Classifier: Framework :: Buildout
Classifier: Intended Audience :: Developers
Classifier: License :: OSI Approved :: BSD License
Classifier: Programming Language :: Python
Classifier: Programming Language :: Python :: 2
Classifier: Programming Language :: Python :: 3
